MANIFEST.in
README.rst
setup.py
torcms_maplet/__init__.py
torcms_maplet.egg-info/PKG-INFO
torcms_maplet.egg-info/SOURCES.txt
torcms_maplet.egg-info/dependency_links.txt
torcms_maplet.egg-info/top_level.txt
torcms_maplet.egg-info/zip-safe
torcms_maplet/core/__init__.py
torcms_maplet/core/router.py
torcms_maplet/core/webdog_to_geojson.py
torcms_maplet/handlers/__init__.py
torcms_maplet/handlers/geojson.py
torcms_maplet/handlers/map_handler.py
torcms_maplet/handlers/mapview_handler.py
torcms_maplet/model/__init__.py
torcms_maplet/model/json_model.py
torcms_maplet/model/layout_model.py
torcms_maplet/model/map_tab.py
torcms_maplet/modules/__init__.py
torcms_maplet/modules/map_modules.py
torcms_maplet/modules/modef.py
torcms_maplet/script/__init__.py
torcms_maplet/script/script_drop_tabels.py
torcms_maplet/script/script_init_tabels.py