Metadata-Version: 1.1
Name: torcms-maplet
Version: 0.0.3
Summary: Maplet 
Home-page: UNKNOWN
Author: bukun
Author-email: bukun@osgeo.cn
License: MIT License
Keywords: torcms,tornado
Platform: any
Classifier: Development Status :: 3 - Alpha
Classifier: Intended Audience :: Developers
Classifier: Topic :: Software Development :: Libraries :: Python Modules
Classifier: License :: OSI Approved :: MIT License
Classifier: Programming Language :: Python :: 3
Classifier: Programming Language :: Python :: 3.5
Classifier: Programming Language :: Python :: 3.6
